README
doap2html.xsl
doapfiend_html.py
hdoap.css
setup.py
doapfiend_html.egg-info/PKG-INFO
doapfiend_html.egg-info/SOURCES.txt
doapfiend_html.egg-info/dependency_links.txt
doapfiend_html.egg-info/entry_points.txt
doapfiend_html.egg-info/requires.txt
doapfiend_html.egg-info/top_level.txt