Metadata-Version: 1.0
Name: doapfiend-html
Version: 0.1.1
Summary: Doapfiend plugin. Serializes DOAP as HTML/CSS.
Home-page: http://trac.doapspace.org/doapfiend/wiki/DfHtml
Author: Rob Cakebread
Author-email: rob@doapspace.org
License: BSD-2
Keywords: doapfiend.plugin doap rdf doapfiend semantic web
Platform: UNKNOWN
Classifier: Development Status :: 2 - Pre-Alpha
Classifier: Intended Audience :: Developers
Classifier: Programming Language :: Python
Classifier: Topic :: Software Development :: Libraries :: Python Modules
